lazy_imports_lite/__init__.py
lazy_imports_lite/__main__.py
lazy_imports_lite/_hooks.py
lazy_imports_lite/_loader.py
lazy_imports_lite/_transformer.py
lazy_imports_lite/_utils.py
hatch_autorun_lazy_imports_lite.pth
lazy_imports_lite-0.1.1.dist-info/METADATA
lazy_imports_lite-0.1.1.dist-info/WHEEL
lazy_imports_lite-0.1.1.dist-info/entry_points.txt
lazy_imports_lite-0.1.1.dist-info/RECORD
