Metadata-Version: 2.1
Name: lazy-imports-lite
Version: 0.1.1
Summary: PEP 690 like lazy imports for python
Project-URL: Documentation, https://github.com/15r10nk/lazy-imports-lite#readme
Project-URL: Issues, https://github.com/15r10nk/lazy-imports-lite/issues
Project-URL: Source, https://github.com/15r10nk/lazy-imports-lite
Author-email: Frank Hoffmann <15r10nk@polarbit.de>
License-Expression: MIT
Classifier: Development Status :: 4 - Beta
Classifier: Programming Language :: Python
Classifier: Programming Language :: Python :: 3.8
Classifier: Programming Language :: Python :: 3.9
Classifier: Programming Language :: Python :: 3.10
Classifier: Programming Language :: Python :: 3.11
Classifier: Programming Language :: Python :: 3.12
Classifier: Programming Language :: Python :: Implementation :: CPython
Classifier: Programming Language :: Python :: Implementation :: PyPy
Requires-Python: >=3.8
